[
null,
{"id":1,"expanded":false,"name":"火车站","order":1,"parentId":0,"scrollX":647.2,"scrollY":556.4},
{"id":2,"expanded":true,"name":"卧铺车厢A","order":2,"parentId":1,"scrollX":655.2,"scrollY":355.6},
{"id":3,"expanded":false,"name":"卧铺车厢B","order":5,"parentId":4,"scrollX":832,"scrollY":640},
{"id":4,"expanded":true,"name":"卧铺车厢C","order":3,"parentId":2,"scrollX":655.2,"scrollY":355.6},
{"id":5,"expanded":true,"name":"卧铺车厢D","order":4,"parentId":4,"scrollX":655.2,"scrollY":355.6},
{"id":6,"expanded":false,"name":"餐车","order":11,"parentId":1,"scrollX":655.2,"scrollY":355.6},
{"id":7,"expanded":false,"name":"货车厢","order":12,"parentId":1,"scrollX":655.2,"scrollY":355.6},
{"id":8,"expanded":true,"name":"卧铺走廊","order":6,"parentId":2,"scrollX":655.2,"scrollY":355.6},
{"id":9,"expanded":false,"name":"卧铺走廊2","order":7,"parentId":8,"scrollX":655.2,"scrollY":355.6},
{"id":10,"expanded":true,"name":"厕所","order":8,"parentId":2,"scrollX":655.2,"scrollY":355.6},
{"id":11,"expanded":true,"name":"硬座车厢1","order":9,"parentId":10,"scrollX":655.2,"scrollY":355.6},
{"id":12,"expanded":false,"name":"硬座车厢1夜晚","order":10,"parentId":11,"scrollX":655.2,"scrollY":355.6},
{"id":13,"expanded":true,"name":"第一幕","order":13,"parentId":0,"scrollX":655.2,"scrollY":355.6},
{"id":14,"expanded":true,"name":"火车站","order":14,"parentId":13,"scrollX":648.8,"scrollY":556.4},
{"id":15,"expanded":true,"name":"卧铺车厢A","order":16,"parentId":19,"scrollX":653.6,"scrollY":350.8},
{"id":16,"expanded":true,"name":"卧铺车厢C","order":20,"parentId":20,"scrollX":655.2,"scrollY":355.6},
{"id":17,"expanded":true,"name":"卧铺车厢D","order":21,"parentId":20,"scrollX":655.2,"scrollY":355.6},
{"id":18,"expanded":false,"name":"卧铺车厢B","order":17,"parentId":19,"scrollX":655.2,"scrollY":355.6},
{"id":19,"expanded":true,"name":"卧铺走廊","order":15,"parentId":13,"scrollX":653.6,"scrollY":350.8},
{"id":20,"expanded":true,"name":"卧铺走廊2","order":19,"parentId":13,"scrollX":655.2,"scrollY":355.6},
{"id":21,"expanded":true,"name":"厕所","order":22,"parentId":20,"scrollX":655.2,"scrollY":355.6},
{"id":22,"expanded":true,"name":"硬座车厢1","order":23,"parentId":13,"scrollX":653.6,"scrollY":350},
{"id":23,"expanded":false,"name":"硬座车厢1夜晚","order":24,"parentId":13,"scrollX":655.2,"scrollY":355.6},
{"id":24,"expanded":false,"name":"餐车","order":25,"parentId":13,"scrollX":655.2,"scrollY":355.6},
{"id":25,"expanded":false,"name":"货车厢","order":26,"parentId":13,"scrollX":655.2,"scrollY":355.6},
{"id":26,"expanded":true,"name":"厕所","order":18,"parentId":19,"scrollX":653.6,"scrollY":350},
{"id":27,"expanded":true,"name":"第二幕","order":27,"parentId":0,"scrollX":653.6,"scrollY":350},
{"id":28,"expanded":true,"name":"卧铺走廊","order":28,"parentId":27,"scrollX":653.6,"scrollY":350},
{"id":29,"expanded":true,"name":"卧铺车厢A","order":29,"parentId":28,"scrollX":655.2,"scrollY":355.6},
{"id":30,"expanded":false,"name":"卧铺车厢B","order":30,"parentId":28,"scrollX":655.2,"scrollY":355.6},
{"id":31,"expanded":true,"name":"厕所","order":31,"parentId":28,"scrollX":832,"scrollY":640},
{"id":32,"expanded":true,"name":"卧铺走廊2","order":32,"parentId":27,"scrollX":653.6,"scrollY":350},
{"id":33,"expanded":true,"name":"卧铺车厢C","order":34,"parentId":32,"scrollX":653.6,"scrollY":350},
{"id":34,"expanded":true,"name":"卧铺车厢D","order":33,"parentId":32,"scrollX":655.2,"scrollY":355.6},
{"id":35,"expanded":true,"name":"厕所","order":35,"parentId":32,"scrollX":655.2,"scrollY":355.6},
null,
null,
null,
{"id":39,"expanded":false,"name":"货车厢","order":36,"parentId":27,"scrollX":653.6,"scrollY":350},
{"id":40,"expanded":true,"name":"第三幕","order":37,"parentId":0,"scrollX":653.6,"scrollY":350},
{"id":41,"expanded":true,"name":"卧铺走廊","order":38,"parentId":40,"scrollX":653.6,"scrollY":350},
{"id":42,"expanded":true,"name":"卧铺车厢A","order":39,"parentId":41,"scrollX":653.6,"scrollY":350},
{"id":43,"expanded":false,"name":"卧铺车厢B","order":40,"parentId":41,"scrollX":655.2,"scrollY":355.6},
{"id":44,"expanded":true,"name":"厕所","order":41,"parentId":41,"scrollX":653.6,"scrollY":350},
{"id":45,"expanded":true,"name":"卧铺走廊2","order":42,"parentId":40,"scrollX":653.6,"scrollY":350},
{"id":46,"expanded":true,"name":"卧铺车厢D","order":43,"parentId":45,"scrollX":653.6,"scrollY":350},
{"id":47,"expanded":true,"name":"卧铺车厢C","order":44,"parentId":45,"scrollX":655.2,"scrollY":355.6},
{"id":48,"expanded":true,"name":"厕所","order":45,"parentId":45,"scrollX":655.2,"scrollY":355.6},
{"id":49,"expanded":false,"name":"硬座车厢1夜晚","order":46,"parentId":40,"scrollX":653.6,"scrollY":350.8},
{"id":50,"expanded":false,"name":"餐车","order":47,"parentId":40,"scrollX":655.2,"scrollY":355.6},
{"id":51,"expanded":false,"name":"货车厢","order":48,"parentId":40,"scrollX":655.2,"scrollY":355.6},
{"id":52,"expanded":true,"name":"硬座车厢1","order":49,"parentId":40,"scrollX":655.2,"scrollY":355.6}
]